{
  "$id": "https://netbeing.net/cheap/hierarchydef.schema.json",
  "$schema": "https://json-schema.org/draft/2020-12/schema",
  "title": "HierarchyDef",
  "description": "Definition of a hierarchy within a catalog in the Cheap data model",
  "type": "object",
  "properties": {
    "name": {
      "type": "string",
      "description": "The unique name identifier for this hierarchy definition"
    },
    "type": {
      "type": "string",
      "enum": ["AM", "EL", "ES", "ED", "ET"],
      "description": "The type of hierarchy: AM=AspectMap, EL=EntityList, ES=EntitySet, ED=EntityDirectory, ET=EntityTree"
    },
    "isModifiable": {
      "type": "boolean",
      "default": true,
      "description": "Whether hierarchies of this type can be modified after creation"
    }
  },
  "required": ["name", "type"]
}